{
  "slug": "design-tools-2026",
  "title": "The State of Design Tools in 2026",
  "description": "The design tools landscape has shifted from feature competition to platform consolidation. We analyze how Figma, Canva, and the Adobe ecosystem are evolving — and what it means for your team's creative workflow.",
  "category": "Design & Creative",
  "tags": [
    "design tools",
    "Figma",
    "Canva",
    "UI/UX",
    "creative workflow",
    "Adobe"
  ],
  "body": "The design tools market in 2026 looks fundamentally different from three years ago. The era of head-to-head feature comparisons — where tools competed on vector editing capabilities or plugin counts — has given way to platform strategy battles. Every major player is building an ecosystem designed to capture teams at every stage of the creative process, from brainstorming through production.\n\n## Figma: From Design Tool to Design Platform\n\nFigma's evolution from a UI design tool into a complete design operations platform is the defining story of the category. After acquiring FigmaJam in 2024 and deeply integrating it into the same workspace, Figma now covers whiteboarding, wireframing, prototyping, design system management, and developer handoff in a single subscription. The 2026 Figma Config announcements doubled down on AI features: auto-layout suggestions that analyze your existing components and propose responsive patterns, a design-to-code pipeline that generates production-ready React components (not just CSS snippets), and an accessibility checker that scans designs against WCAG 2.2 criteria before they reach development. These moves position Figma as the operating system for digital product design, making it increasingly difficult for specialized tools to compete on integration alone.\n\n## Canva: The Enterprise Creative Platform\n\nCanva's trajectory has been equally ambitious but targets a different market segment. Once dismissed as a template-based tool for non-designers, Canva now serves over 100 million monthly active users and has made serious inroads into enterprise marketing teams with its Visual Suite — a connected ecosystem of design, presentation, document, and whiteboard tools. The 2026 releases focus on brand governance at scale: Magic Brand Templates that lock typography, color, and logo usage across an entire organization while allowing individual teams to customize layouts within those constraints. Canva's AI image generation, integrated directly into the editor rather than through plugins, has reached a quality level that replaces stock photo subscriptions for many teams. The trade-off remains: Canva excels at speed and accessibility but still lacks the pixel-level control and developer handoff fidelity that product design teams require.\n\n## Adobe: Bundling for Retention\n\nAdobe's strategy in 2026 is ecosystem bundling. The Firefly generative AI models are now embedded across Photoshop, Illustrator, and After Effects, enabling text-to-vector graphics, generative fill for video, and automatic rotoscoping. Adobe's bet is that professionals who need the full creative toolkit — photo editing, vector illustration, video production, and motion design — will stay within Creative Cloud because assembling equivalent capabilities from point solutions costs more in both money and workflow friction. The challenge for Adobe is that fewer teams actually need this breadth. Most organizations have split into specialized roles: UI designers use Figma, marketers use Canva, and only dedicated production artists use the full Adobe stack. Adobe Express, the company's answer to Canva in the quick-content space, has grown but remains a distant third in that segment.\n\n## Comparing the Platforms\n\nFor most teams in 2026, the design tool decision is not about which tool is objectively best — it is about which ecosystem best fits your team's primary output. Product teams building digital interfaces should build on Figma for its end-to-end workflow from wireframing to production code. Marketing teams producing brand content at volume should center on Canva for its speed, template library, and brand governance features. Production houses and agencies that create across print, video, and digital should evaluate Adobe for its unmatched breadth. Few teams benefit from maintaining two ecosystems simultaneously — the integration and file-format translation overhead rarely justifies the flexibility of having both.\n\n## What This Means for Your Stack\n\nThe 2026 design tools landscape favors consolidation. The strongest argument for standardizing on one platform is that every additional tool in your creative workflow introduces friction in file sharing, version tracking, feedback collection, and approval routing. Before adding a new tool, ask whether it integrates with your primary design platform at the API level — native integrations between design tools are rare, and teams that rely on manual export-import workflows between platforms tend to abandon the secondary tool within six months. The companies that will navigate this landscape best are those that pick a primary platform aligned with their core output, invest deeply in mastering it, and resist the temptation to chase features in competing tools that duplicate what their primary platform can already do with proper configuration.",
  "author": "StackPilot Team",
  "publishedAt": "2026-07-16",
  "readingTime": 9,
  "relatedPosts": [
    "software-review-methodology"
  ],
  "relatedGuides": [
    "design-software-buyers-guide"
  ],
  "relatedComparisons": [
    "figma-vs-sketch"
  ],
  "relatedGlossary": [
    "ux",
    "saas"
  ]
}
