{
  "slug": "confluence",
  "name": "Confluence",
  "tagline": "Team collaboration and knowledge management hub",
  "description": "Create, share, and organize team knowledge with connected documentation",
  "category": "Project Management",
  "website": "https://www.atlassian.com/software/confluence",
  "pricing": "Freemium",
  "priceRange": "Free–$11/user/mo",
  "rating": 4.1,
  "reviewCount": 32400,
  "pros": [
    "Deep Jira integration linking documentation to developer workflows",
    "Whiteboards with action items converting into Jira tickets",
    "300+ templates for engineering, product, and business documentation",
    "Spaces with granular permissions for org-wide knowledge management",
    "Confluence AI summarizing pages and suggesting related content"
  ],
  "cons": [
    "Search effectiveness declines significantly across 5,000+ pages",
    "Page editor feels dated versus Notion's block-based system",
    "Self-hosted Data Center pricing exceeds $40K/year for 500 users"
  ],
  "features": [
    {
      "name": "Pages",
      "description": "Rich text with inline comments",
      "available": true,
      "category": "Core"
    },
    {
      "name": "Spaces",
      "description": "Organized content workspaces",
      "available": true,
      "category": "Core"
    },
    {
      "name": "Whiteboards",
      "description": "Visual collaboration with Jira sync",
      "available": true,
      "category": "Core"
    },
    {
      "name": "Templates",
      "description": "300+ pre-built document types",
      "available": true,
      "category": "Core"
    },
    {
      "name": "Databases",
      "description": "Structured table content",
      "available": true,
      "category": "Core"
    },
    {
      "name": "Blogs",
      "description": "Team news and updates",
      "available": true,
      "category": "Core"
    },
    {
      "name": "Analytics",
      "description": "Page views and engagement",
      "available": true,
      "category": "Analytics"
    },
    {
      "name": "Permissions",
      "description": "Space and page-level access",
      "available": true,
      "category": "Security"
    },
    {
      "name": "AI",
      "description": "Page summaries and content generation",
      "available": true,
      "category": "AI"
    },
    {
      "name": "Smart Links",
      "description": "Rich previews for 500+ integrations",
      "available": true,
      "category": "Core"
    },
    {
      "name": "Macros",
      "description": "Dynamic content widgets",
      "available": true,
      "category": "Core"
    },
    {
      "name": "Labels",
      "description": "Taxonomy and content tagging",
      "available": true,
      "category": "Core"
    },
    {
      "name": "Version History",
      "description": "Track page changes",
      "available": true,
      "category": "Core"
    },
    {
      "name": "Comments",
      "description": "Inline and page-level discussion",
      "available": true,
      "category": "Core"
    },
    {
      "name": "Search",
      "description": "Global and space-scoped search",
      "available": true,
      "category": "Core"
    },
    {
      "name": "Atlassian Intelligence",
      "description": "AI across Confluence and Jira",
      "available": true,
      "category": "AI"
    },
    {
      "name": "API",
      "description": "RESTful and GraphQL",
      "available": true,
      "category": "Integrations"
    },
    {
      "name": "Migration Tools",
      "description": "Cloud and on-prem import",
      "available": true,
      "category": "Advanced"
    }
  ],
  "ratings": [
    {
      "label": "Ease of Use",
      "score": 3.8
    },
    {
      "label": "Features",
      "score": 4.2
    },
    {
      "label": "Performance",
      "score": 4
    },
    {
      "label": "Support",
      "score": 3.7
    },
    {
      "label": "Value",
      "score": 4
    }
  ],
  "content": [
    {
      "title": "Executive Summary",
      "body": "Create, share, and organize team knowledge with connected documentation Confluence earns a 4.1/5 rating from 32,400 user reviews.",
      "type": "text"
    },
    {
      "title": "TL;DR",
      "body": "Confluence is a leading project management platform rated 4.1/5 across 32,400 reviews. Pricing starts at Free–$11/user/mo. Best for Engineering Teams and Product Teams.",
      "type": "text"
    },
    {
      "title": "Rating Overview",
      "body": "Confluence scores 4.1/5 overall with ease of use (3.8/5), features (4.2/5), performance (4/5), support (3.7/5), value (4/5).",
      "type": "text"
    },
    {
      "title": "Quick Verdict",
      "body": "Confluence earns a 4.1/5 rating recommended for Engineering Teams and Product Teams. Delivers solid functionality with functional design.",
      "type": "text"
    },
    {
      "title": "Company Background",
      "body": "Confluence was founded in 2004 in San Francisco, USA, serving 100K+ teams customers with 5,000+ employees.",
      "type": "text"
    },
    {
      "title": "Product Overview",
      "body": "Confluence is a team collaboration and knowledge management hub. Provides 18 features across Core, Analytics, Security, AI, Integrations, Advanced categories. Self-hosted available. Mobile on iOS and Android. API available.",
      "type": "text"
    },
    {
      "title": "Key Features",
      "body": "Essential project management features:",
      "type": "list",
      "items": [
        "Pages: Rich text with inline comments.",
        "Spaces: Organized content workspaces.",
        "Whiteboards: Visual collaboration with Jira sync.",
        "Templates: 300+ pre-built document types.",
        "Databases: Structured table content.",
        "Blogs: Team news and updates."
      ]
    },
    {
      "title": "Feature Deep Dive",
      "body": "Pages. Rich text with inline comments. Spaces. Organized content workspaces. Whiteboards. Visual collaboration with Jira sync.",
      "type": "text"
    },
    {
      "title": "AI Features",
      "body": "Confluence AI includes AI content suggestions, Smart search, AI page summaries.",
      "type": "text"
    },
    {
      "title": "API & Automation",
      "body": "Confluence provides a comprehensive API for custom integration and workflow automation.",
      "type": "text"
    },
    {
      "title": "Security",
      "body": "Confluence holds SOC 2 Type II, ISO 27001, GDPR, HIPAA, FedRAMP certifications with TLS 1.2+ and AES-256 encryption.",
      "type": "text"
    },
    {
      "title": "Compliance",
      "body": "Confluence complies with GDPR, CCPA, HIPAA, SOC 2 regulations.",
      "type": "text"
    },
    {
      "title": "Integrations",
      "body": "Integrates with Jira, Slack, Trello, GitHub, Google Drive, Microsoft Teams, Figjam, Draw.io, and 2+ more.",
      "type": "text"
    },
    {
      "title": "Pricing",
      "body": "Confluence uses freemium with per-user premium. Free tier available. Plans from Free–$11/user/mo.",
      "type": "text"
    },
    {
      "title": "Pros",
      "body": "Confluence advantages:",
      "type": "list",
      "items": [
        "Deep Jira integration linking documentation to developer workflows",
        "Whiteboards with action items converting into Jira tickets",
        "300+ templates for engineering, product, and business documentation",
        "Spaces with granular permissions for org-wide knowledge management"
      ]
    },
    {
      "title": "Cons",
      "body": "Considerations:",
      "type": "list",
      "items": [
        "Search effectiveness declines significantly across 5,000+ pages",
        "Page editor feels dated versus Notion's block-based system",
        "Self-hosted Data Center pricing exceeds $40K/year for 500 users"
      ]
    },
    {
      "title": "Performance",
      "body": "Adequate performance for most use cases.",
      "type": "text"
    },
    {
      "title": "Ease of Use",
      "body": "Moderate learning curve with comprehensive documentation.",
      "type": "text"
    },
    {
      "title": "User Experience",
      "body": "Functional organized interface.",
      "type": "text"
    },
    {
      "title": "Customer Support",
      "body": "Support rated 3.7/5 via email and knowledge base.",
      "type": "text"
    },
    {
      "title": "Industry Fit",
      "body": "Best for Knowledge Management and Collaboration with Engineering Teams and Product Teams teams.",
      "type": "text"
    },
    {
      "title": "Team Size Fit",
      "body": "Confluence accommodates teams of all sizes with generous free tier. Best ROI for 5-50 person teams.",
      "type": "text"
    },
    {
      "title": "Real Use Cases",
      "body": "A engineering teams team uses Confluence to streamline project management workflows and improve team productivity.",
      "type": "text"
    },
    {
      "title": "Competitor Analysis",
      "body": "Confluence competes with notion, monday-com, asana. Primary differentiators: core functionality and pricing.",
      "type": "text"
    },
    {
      "title": "Alternatives",
      "body": "Consider notion, monday-com, asana based on specific team requirements.",
      "type": "text"
    },
    {
      "title": "Migration Guide",
      "body": "Migration rated moderate complexity. Budget 2-4 weeks for full transition. Parallel testing recommended.",
      "type": "text"
    },
    {
      "title": "Buying Advice",
      "body": "Evaluate: feature alignment, total cost at Free–$11/user/mo, migration effort (2-4 weeks), and real-data trial.",
      "type": "text"
    },
    {
      "title": "Final Verdict",
      "body": "Confluence earns 4.1/5. Solid option for most teams. Recommended for teams prioritizing project management.",
      "type": "text"
    },
    {
      "title": "Pricing at a Glance",
      "body": "pricing-ladder",
      "type": "diagram"
    },
    {
      "title": "Feature Radar",
      "body": "feature-radar",
      "type": "diagram"
    },
    {
      "title": "Implementation Flow",
      "body": "implementation-flow",
      "type": "diagram"
    }
  ],
  "faqs": [
    {
      "question": "What is Confluence best used for?",
      "answer": "Confluence is best used for create, share, and organize team knowledge with connected documentation."
    },
    {
      "question": "How much does Confluence cost?",
      "answer": "Confluence uses freemium with per-user premium starting at Free–$11/user/mo. Free tier available."
    },
    {
      "question": "Does Confluence integrate with other tools?",
      "answer": "Yes, integrates with Jira, Slack, Trello, GitHub, Google Drive. And 5+ more."
    },
    {
      "question": "Is Confluence suitable for small teams?",
      "answer": "Yes, with a generous free tier. Freemium with per-user premium scales with team growth."
    },
    {
      "question": "How does Confluence pricing work?",
      "answer": "Confluence uses freemium with per-user premium from Free–$11/user/mo, with free tier available."
    },
    {
      "question": "Is Confluence secure?",
      "answer": "Yes, holds SOC 2 Type II, ISO 27001, GDPR, HIPAA, FedRAMP certifications with encryption."
    },
    {
      "question": "What integrations does Confluence offer?",
      "answer": "Integrates with Jira, Slack, Trello, GitHub, Google Drive, Microsoft Teams, and more. API available."
    },
    {
      "question": "Is Confluence good for small businesses?",
      "answer": "Yes, with free tier. Freemium with per-user premium scales with business size."
    },
    {
      "question": "What are Confluence's main advantages?",
      "answer": "Deep Jira integration linking documentation to developer wor and Whiteboards with action items converting into Jira tickets."
    },
    {
      "question": "What are Confluence's limitations?",
      "answer": "Search effectiveness declines significantly across 5,000+ pages and Page editor feels dated versus Notion's block-based system."
    },
    {
      "question": "How does Confluence compare to notion?",
      "answer": "Confluence differentiates through pricing and performance."
    },
    {
      "question": "Does Confluence support team collaboration?",
      "answer": "Yes, includes collaboration features for team workflows."
    },
    {
      "question": "Can I customize Confluence?",
      "answer": "Yes, via API, custom fields, and templates."
    },
    {
      "question": "Is Confluence easy to set up?",
      "answer": "Setup takes a few days with documentation support."
    },
    {
      "question": "How often does Confluence update?",
      "answer": "Updates monthly."
    },
    {
      "question": "What support does Confluence provide?",
      "answer": "Support rated 3.7/5. Email and knowledge base."
    },
    {
      "question": "Does Confluence offer a free version?",
      "answer": "Yes, with core features."
    },
    {
      "question": "How does Confluence handle data privacy?",
      "answer": "Complies with GDPR, CCPA, HIPAA, SOC 2 regulations."
    },
    {
      "question": "What ROI can teams expect?",
      "answer": "Positive ROI typically within 3-6 months from improved project management workflows."
    },
    {
      "question": "What platforms does Confluence support?",
      "answer": "Available on Cloud, Self-hosted. Mobile on iOS and Android."
    }
  ],
  "alternatives": [
    "notion",
    "monday-com",
    "asana"
  ],
  "relatedComparisons": [],
  "relatedGuides": [
    "remote-team-collaboration-guide"
  ],
  "relatedPosts": [],
  "lastReviewed": "2026-07-19",
  "author": "StackPilot Team",
  "company": {
    "founded": 2004,
    "headquarters": "San Francisco, USA",
    "customers": "100K+ teams",
    "employeeCount": "5,000+",
    "industries": [
      "Knowledge Management",
      "Collaboration",
      "SaaS"
    ],
    "targetUsers": [
      "Engineering Teams",
      "Product Teams",
      "Enterprise"
    ],
    "pricingModel": "Freemium with per-user premium",
    "deployment": [
      "Cloud",
      "Self-hosted"
    ],
    "securityCertifications": [
      "SOC 2 Type II",
      "ISO 27001",
      "GDPR",
      "HIPAA",
      "FedRAMP"
    ],
    "compliance": [
      "GDPR",
      "CCPA",
      "HIPAA",
      "SOC 2"
    ],
    "integrations": [
      "Jira",
      "Slack",
      "Trello",
      "GitHub",
      "Google Drive",
      "Microsoft Teams",
      "Figjam",
      "Draw.io",
      "GitLab",
      "Zoom"
    ],
    "apiAvailable": true,
    "aiFeatures": [
      "AI content suggestions",
      "Smart search",
      "AI page summaries"
    ],
    "mobileApps": [
      "iOS",
      "Android"
    ],
    "learningCurve": "Moderate",
    "migrationComplexity": "Moderate",
    "supportQuality": "4.0/5",
    "releaseFrequency": "Monthly"
  },
  "difficulty": "Advanced",
  "learningCurve": "Steep — requires dedicated training time for full proficiency",
  "whoShouldUse": "Confluence is ideal for small to mid-size teams that need a reliable project management solution without excessive complexity. It works well for organizations with 5-200 users who prioritize ease of use and quick deployment.",
  "whoShouldNotUse": "Confluence may be overwhelming for users who only need basic project management functionality. Its extensive feature set can create unnecessary complexity for simple use cases."
}