{
  "slug": "i18n",
  "term": "Internationalization (i18n)",
  "definition": "The process of designing software so it can be adapted to various languages and regions without engineering changes.",
  "extendedDefinition": "The process of designing software so it can be adapted to various languages and regions without engineering changes.",
  "category": "Developer Tools",
  "examples": [],
  "relatedTerms": [
    "localization",
    "ux"
  ],
  "description": "Internationalization (i18n). The process of designing software so it can be adapted to various languages and regions without engineering changes."
}
