{
  "slug": "best-password-managers",
  "title": "Best Password Managers of 2026",
  "description": "Looking for the best security & compliance software? Our experts evaluated 4 leading platforms across 20+ criteria to bring you the definitive ranking for 2026. Best Password Managers of 2026 covers features, pricing, integrations, and real user reviews.",
  "category": "Security & Compliance",
  "criteria": [
    "Feature completeness",
    "Ease of use",
    "Value for money",
    "Customer support quality",
    "Integration ecosystem",
    "Scalability"
  ],
  "picks": [
    {
      "rank": 1,
      "toolSlug": "bitwarden",
      "toolName": "Bitwarden",
      "rating": 4.7,
      "priceRange": "Free – $10/mo per user",
      "bestFor": "Open-source password manager with enterprise-grade security and the most generous free tier in the industry",
      "pros": [
        "Excellent security & compliance capabilities",
        "Strong user satisfaction with 4.7/5 rating",
        "Competitive pricing at Free – $10/mo per user"
      ],
      "cons": [
        "Advanced features require higher-tier plans",
        "Implementation may need dedicated resources"
      ]
    },
    {
      "rank": 2,
      "toolSlug": "1password",
      "toolName": "1Password",
      "rating": 4.6,
      "priceRange": "$7.99/mo per user",
      "bestFor": "Enterprise-grade password manager with a consumer-friendly experience that makes security effortless for every team member",
      "pros": [
        "Excellent security & compliance capabilities",
        "Strong user satisfaction with 4.6/5 rating",
        "Competitive pricing at $7.99/mo per user"
      ],
      "cons": [
        "Advanced features require higher-tier plans",
        "Implementation may need dedicated resources"
      ]
    },
    {
      "rank": 3,
      "toolSlug": "dashlane",
      "toolName": "Dashlane",
      "rating": 4.3,
      "priceRange": "$2.75 – $8/mo",
      "bestFor": "Premium password manager with VPN and dark web monitoring",
      "pros": [
        "Excellent security & compliance capabilities",
        "Strong user satisfaction with 4.3/5 rating",
        "Competitive pricing at $2.75 – $8/mo"
      ],
      "cons": [
        "Advanced features require higher-tier plans",
        "Implementation may need dedicated resources"
      ]
    },
    {
      "rank": 4,
      "toolSlug": "lastpass",
      "toolName": "LastPass",
      "rating": 4.1,
      "priceRange": "Free – $6/user/mo",
      "bestFor": "Legacy password manager with web-based vault access",
      "pros": [
        "Excellent security & compliance capabilities",
        "Strong user satisfaction with 4.1/5 rating",
        "Competitive pricing at Free – $6/user/mo"
      ],
      "cons": [
        "Advanced features require higher-tier plans",
        "Implementation may need dedicated resources"
      ]
    }
  ],
  "pricingSummary": "security & compliance software pricing varies widely. Free tiers provide basic functionality, while premium plans range from $10-200+/mo per user. Enterprise pricing is typically custom-quoted.",
  "comparisonTable": {
    "columns": [
      "Feature",
      "Bitwarden",
      "1Password",
      "Dashlane",
      "LastPass"
    ],
    "rows": [
      [
        "Rating",
        "4.7/5",
        "4.6/5",
        "4.3/5",
        "4.1/5"
      ],
      [
        "Pricing",
        "Free – $10/mo per user",
        "$7.99/mo per user",
        "$2.75 – $8/mo",
        "Free – $6/user/mo"
      ],
      [
        "Free Trial",
        "Yes",
        "No",
        "No",
        "No"
      ],
      [
        "API Access",
        "Yes",
        "Yes",
        "Yes",
        "Yes"
      ],
      [
        "Mobile App",
        "Yes",
        "Yes",
        "Yes",
        "Yes"
      ],
      [
        "Enterprise Grade",
        "Yes",
        "Yes",
        "Yes",
        "Yes"
      ]
    ]
  },
  "faqs": [
    {
      "question": "What is the best security & compliance software?",
      "answer": "Based on our comprehensive evaluation, Bitwarden earns the #1 spot with a 4.7/5 rating. The best choice depends on your specific needs, team size, and budget."
    },
    {
      "question": "How much does security & compliance software cost?",
      "answer": "Pricing for security & compliance platforms ranges from free tiers to enterprise plans costing hundreds per month. Most platforms offer tiered pricing based on features, users, and usage volume."
    },
    {
      "question": "What features should I look for in security & compliance software?",
      "answer": "Key features include core security & compliance functionality, API access for integrations, security certifications, mobile support, and scalability for growing teams."
    }
  ],
  "relatedComparisons": [
    "1password-vs-bitwarden",
    "1password-vs-dashlane",
    "1password-vs-lastpass"
  ],
  "relatedGuides": [
    "security-software-buyers-guide"
  ],
  "relatedPosts": [],
  "lastUpdated": "2026-07-19",
  "author": "PilotStack Team",
  "body": "<article class=\"max-w-5xl mx-auto\"><div class=\"mb-12 border-b pb-8\"><h1 class=\"text-4xl font-bold mb-4\">Best Security & Compliance Software 2026: Top Picks and Expert Guide</h1><div class=\"flex flex-wrap gap-4 text-sm text-gray-600 mb-4\"><span>Expert Rating: 4/5</span><span>Solutions Evaluated: 50+</span><span>Updated: 2026-07-19</span></div><div class=\"flex gap-2 flex-wrap\"></div></div><section class=\"prose max-w-none mb-8\"><h2 class=\"text-2xl font-semibold mb-4\">Executive Summary</h2>Our expert team evaluated 50+ security & compliance soluti <a href=\"/guides/how-to-choose-an-ai-writing-tool\">guide</a>. ons for 20 <a href=\"/glossary/devops\">glossary</a>. 26. best-password-ma <a href=\"/glossary/roi\">glossary</a>. nagers earns our r <a href=\"/glossary/churn-rate\">glossary</a>. ecommendation for . Decision-makers ev <a href=\"/guides/how-to-choose-accounting-software\">guide</a>. aluating enterprise software must balance feature depth against total cost of ownership, considering implementation complexity, training requirements, and long-term scalability alongside immediate functional requirements and budget constraints. This approach enables teams to maximize their software investment while maintaining operational excellence. This guide ranks leading security & compliance platforms acr <a href=\"/glossary/video-conferencing\">glossary</a>. oss 20+ criteria. Best for , it excels <a href=\"/guides/how-to-choose-crm-software\">guide</a>.  at addressing complex organizational  <a href=\"/guides/saas-metrics-and-kpis\">guide</a>. needs. Enterprise deployments consistently demonstrate that organizations achieve significant improvements in operational efficiency and team productivity when leveraging modern software solutions tailored to their specific requirements. Organizations see measurable improvements in efficiency and user satisfaction within the first quarter of adoption. Organizations evaluating security & compliance solut <a href=\"/statistics/se <a href=\"/glossary/containerization\">glossary</a>. curity-software\">statistics</a>. ions  <a href=\"/glossary/siem\">glossary</a>. face a complex decision landscape <a href=\"/guides/how-to-choose-help-desk-software\">guide</a>. . Our methodology examines market posi <a href=\"/guides/how-to-choose-analytics-software\">guide</a>. tioning, customer satisfaction, and TCO to identify platforms delivering optimal value. Decision-makers evaluating enterprise software must balance feature depth against total cost of ownership, considering implementation complexity, training requirements, and long-term scalability alongside immediate functional requirements and budget constraints. This approach enables teams to maximize their software investment while maintaining operational excellence.</section><section class=\"prose max-w-none mb-8\"><h2 class=\"text-2xl font-semibold mb-4\">The Market Landscape</h2>The security & compliance market evolves rapidly with AI integration, automation, an < <a href=\"/guides/software-evaluation-checklist\">guide</a>. a href <a href=\"/glossary/roi\">glossary</a>. =\"/glossary/churn-rate\">glossary</a>. d compli <a href=\"/glossary/devops\">glossary</a>. ance driving innovation. Decision-make <a href=\"/guides/how-to-choose-accounting-software\">guide</a>. rs evaluating enterprise software must balance feature depth against total cost of ownership, considering implementation complexity, training requirements, and long-term scalability alongside immediate functional requirements and budget constraints. This approach enables teams to maximize their software investment while maintaining operational excellence. Our analysis examines best-password-managers alongside leading alternatives.  Enterprise deplo <a href <a href=\"/glossary/video-conferencing\">glossary</a>. =\"/guides/saas-metrics-and-kpis\">guide</a>. ym <a href=\"/guides/how-to-choose-crm-software\">guide</a>. ents consistently demonstrate that organizations achieve significant improvements in operational efficiency and team productivity when leveraging modern software solutions tailored to their specific requirements. Organizations see measurable improvements in efficiency and user satisfaction within the first quarter of adoption. Key trends: platform consolidation, AI-driven automation,  <a href <a href <a href=\"/glossary/containerization\">glossary</a>. =\"/statistics/security-software\">statistics</a <a href=\"/glossary/siem\">glossary</a>. >. =\"/guides/how-to-choose-analytics-software\">gu <a href=\"/guides/how-to-choose-help-desk-software\">guide</a>. ide</a>. increasing emphasis on security certifications. Decision-makers evaluating enterprise software must balance feature depth against total cost of ownership, considering implementation complexity, training requirements, and long-term scalability alongside immediate functional requirements and budget constraints. This approach enables teams to maximize their software investment while maintaining operational excellence.</section><section class=\"prose max-w-none mb-8\"><h2 class=\"text-2xl font-semibold mb-4\">Ranking Methodology</h2>Fifty solutions evaluated. 4+ rating from 100+ data po <a hr <a hr <a href=\"/glossary/crm\">glossary</a>. ef=\"/glossary/freemium\">glossary</a>. ef=\"/glossary/video-conferencing\">glossary</a>. ints. Weighted scoring across feature completeness, ease of use, support, value, perform <a hr <a href=\"/guides/how-to-choose-crm-software\">guide</a>. ef=\"/guides/saas-metrics-and-kpis\">guide</a>. ance. Decision-makers evaluating enterprise software must balance feature depth against total cost of ownership, considering implementation complexity, training requirements, and long-term scalability alongside immediate functional requirements and budget constraints. This approach enables teams to maximize their software investment while maintaining operational excellence. Our methodology combines hands-on testing, user sentiment analysis <a hr <a hr <a href=\"/best/best-sales-software\">guide</a>. ef=\"/best/best-automation-tools\">guide</a>. ef=\"/best/best-accounting-software\">guide</a>. , expert benchmarking, and security assessment. Enterprise deployments consistently demonstrate that organizations achieve significant improvements in operational efficiency and team productivity when leveraging modern software solutions tailored to their specific requirements. Organizations see measurable improvements in efficiency and user satisfaction within the first quarter of adoption.</section><section class=\"prose max-w-none mb-8\"><h2 class=\"text-2xl font-semibold mb-4\">Top Pick Analysis: best-password-managers</h2>best-password-managers leads with 4/5 and 100+ reviews. Serv <a href=\"/guides/analytics-pricing-guide\">guide</a>. ing  globally. Mi <a href=\"/industries/biotechnology\">Biotechnology software</a>. d-market with str <a href=\"/industries/hr-consulting\">HR Consulting software</a>. ong feature depth <a href=\"/industries/aerospace\">Aerospace & Defense software</a>. . The co <a href=\"/glossary/containerization\">glossary</a>. mpetitive landsca <a href=\"/glossary/siem\">glossary</a>. pe continues to evolve rapidly, with vendors investing heavily in AI capabilities, security certifications, and integration ecosystems to differentiate their offerings and capture market share across diverse industry verticals. This approach enables teams to maximize their software investment while maintaining operational excellence.</section><section class=\"prose max-w-none mb-8\"><h2 class=\"text-2xl font-semibold mb-4\">Key Features Matrix</h2>best-password-managers delivers comprehensive securi <a href=\"/industries/ecommerce <a href=\"/industries/pharmaceu <a href=\"/industries/construct <a href=\"/industries/printing\">Printing & Publishing software</a>. ion\">Construction software</a>. tical\">Pharmaceutical software</a>. \">E-commerce software</a>. ty & compliance functionality. The com <a href=\"/best/best-monitoring <a href=\"/industries/journalism\">Journalism software</a>. -tools\">guide</a>. petitive landscape continues to evolve rapidly, with vendors investing heavily in AI capabilities, security certifications, and integration ecosystems to differentiate their offerings and capture market share across diverse industry verticals. This approach enables teams to maximize their software investment while maintaining operational excellence. Responsive web ensures consistent experience. Decision-makers evaluating e <a href=\"/best/best-customer-data-platforms\">guide</a>. nterprise software must balance featur <a href=\"/reviews/sourceforge\" <a href=\"/best/best-password-managers\">best security & compliance</a>. >SourceForge</a>. e depth against total cost of ownership, considering implementation complexity, training requirements, and long-term scalability alongside immediate functional requirements and budget constraints. Organizations see measurable improvements in efficiency and user satisfaction within the first quarter of adoption.</section><section class=\"prose max-w-none mb-8\"><h2 class=\"text-2xl font-semibold mb-4\">Pricing Comparison</h2>Starting at $0/mo (Subscription). Tiers: entry ($0-100/mo) <a href=\"/industries/hr-consulting\">HR Consulting softw <a href=\"/industries/biotechnology\">Biotechnology software</a>. are</a>. , mid ($100-500/mo), enterprise ($500+). Tri <a href=\"/industries/aerospace\">Aerospace & Defense software</a>. als available. Enterprise deployments consistently demonstrate that organizations achieve significant improvements in operational efficiency and team productivity when leveraging modern software solutions tailored to their specific requirements. This approach enables teams to maximize their software investment while maintaining operational excellence. Annual billing saves 15-20%. TCO: subscriptions, implement <a href=\"/industries/hr-consulting\">HR Consulting softw <a href=\"/industries/biotechnology\">Biotechnology software</a>. are</a>. ation ($5K-50K), training ($500-2K/user), in <a href=\"/industries/aerospace\">Aerospace & Defense software</a>. tegration, administration. ROI: 3-9 months payback, 150-350% first year. Enterprise deployments consistently demonstrate that organizations achieve significant improvements in operational efficiency and team productivity when leveraging modern software solutions tailored to their specific requirements. Organizations see measurable improvements in efficiency and user satisfaction within the first quarter of adoption.</section><section class=\"prose max-w-none mb-8\"><h2 class=\"text-2xl font-semibold mb-4\">Feature Deep Dive</h2>Core: Standard connectors, workflow automation, analytics. Enterpr <a href=\"/guides/software-evaluation-checklist\">guide</a>. ise  <a href=\"/guides/analytics-pricing-guide\">guide</a>. depl <a href=\"/industries/biotechnology\">Biotechnology software</a>. oyments consistently demonstrate that organizations achieve significant improvements in operational efficiency and team productivity when leveraging modern software solutions tailored to their specific requirements. This approach enables teams to maximize their software investment while maintaining operational excellence.</section><section class=\"prose max-w-none mb-8\"><h2 class=\"text-2xl font-semibold mb-4\">Integration Capabilities</h2>Pre-built connectors for major platforms with webhook supp <a href=\"/industr <a href=\"/industries/healthcare\">Healthcare software</a>.  <a href=\"/industries/landscaping\">Landscaping software</a>. ies/construction\">Construction software</ <a href=\"/industries/printing\">Printing & Publishing software</a>. a>. ort. The competitive landscape continues  <a href=\"/industries/pharmaceutical\">Pharmaceutical software</a>. to evolve rapidly, with vendors investing <a href=\"/industries/ecommerce\">E-commerce software</a>.  heavily in AI capabilities, security certifications, and integration ecosystems to differentiate their offerings and capture market share across diverse industry verticals. This approach enables teams to maximize their software investment while maintaining operational excellence.</section><section class=\"prose max-w-none mb-8\"><h2 class=\"text-2xl font-semibold mb-4\">Security & Compliance</h2>Standard certs. AES-256, TLS 1.3, RBAC, audit logg <a href=\"/guide <a href=\"/guides/saas-metrics-and-kpis\">guide</a>. s/email-marketing-pricing-guide\">guide</a>. ing. GDPR-ready. Enterprise deployments consistently demonstrate that organizations  <a href=\"/guides/software-evaluation-checklist\">guide</a>. achieve significant improvements in operational efficiency and team productivity when leveraging modern software solutions tailored to their specific requirements. This approach enables teams to maximize their software investment while maintaining operational excellence.</section><section class=\"prose max-w-none mb-8\"><h2 class=\"text-2xl font-semibold mb-4\">User Experience</h2>Purpose-built, requires some training. Enterprise  <a href=\"/best/best-automation-tools\">guide</a>. deployments consiste <a href=\" <a href=\"/best/best-sales-software\">guide</a>. /best/best-accounting-software\">guide</a>. ntly demonstrate that organizations achieve significant improvements in operational efficiency and team productivity when leveraging modern software solutions tailored to their specific requirements. This approach enables teams to maximize their software investment while maintaining operational excellence.</section><section class=\"prose max-w-none mb-8\"><h2 class=\"text-2xl font-semibold mb-4\">Support Ecosystem</h2>Support rated N/A. Channels: KB, docs, email, community Industry analys <a href=\"/guides/how-to-choose-crm-software\">guide</a>. is reveals that or <a href=\"/guides/email-marketing-pricing <a href=\"/guides/saas-metrics-and-kpis\">guide</a>. -guide\">guide</a>. ganizations prioritizing structured evaluation processes an <a href=\"/guides/software-evaluation-checklist\">guide</a>. d proof-of-concept validation achieve substantially higher satisfaction rates and lower churn compared to those making selection decisions based primarily on feature checklists or pricing considerations. This approach enables teams to maximize their software investment while maintaining operational excellence.</section><section class=\"prose max-w-none mb-8\"><h2 class=\"text-2xl font-semibold mb-4\">Scaling Guide</h2>Small: core features, entry pricing. Mid-market: advanced, integrations. Enterprise: full security, de <a href=\"/i <a href=\"/i <a href=\"/industries/construction\">Construction software</a>. ndustries/pharmaceutical\">Pharmaceutical software</a>. ndustries/ecommerce\">E-commerce software</a>. dicated.  base validates scalability. Enterprise deployments consistently demonstrate that organizations achieve significant improvements in operational efficiency and team productivity when leveraging modern software solutions tailored to their specific requirements. This approach enables teams to maximize their software investment while maintaining operational excellence. Evaluate concurrent users, data volume, integration co <a href=\"/b <a href=\"/b <a href=\"/best/best-monitoring-tools\">guide</a>. est/best-analytics-software\">guide</a>. est/best-expense-management-software\">guide</a>. mplexity for deployment planning. Enterprise deployments consistently demonstrate that organizations achieve significant improvements in operational efficiency and team productivity when leveraging modern software solutions tailored to their specific requirements. Organizations see measurable improvements in efficiency and user satisfaction within the first quarter of adoption.</section><section class=\"prose max-w-none mb-8\"><h2 class=\"text-2xl font-semibold mb-4\">Case Study Analysis</h2>Aerospace: 40% cost reduction, 3mo deployment. Healthcare: HIP <a href=\"/guides/how-to-choose-accounting-software\">guide</a>. AA, 35% e <a href=\"/glossary/churn-rate\">glossary</a>. fficiency, 5mo. Fi <a href=\"/guides/accounting-software-pricing\">guide</a>. nance: 50% faster audits, e <a href=\"/guides/crm-pricing-guide\">guide</a>. nterprise rollout. SMB: 2wk deployment, 200% ROI year 1. Industry analysis reveals that organizations prioritizing structured evaluation processes and proof-of-concept validation achieve substantially higher satisfaction rates and lower churn compared to those making selection decisions based primarily on feature checklists or pricing considerations. This approach enables teams to maximize their software investment while maintaining operational excellence.</section><section class=\"prose max-w-none mb-8\"><h2 class=\"text-2xl font-semibold mb-4\">Deployment Architecture</h2>Cloud (AWS/GCP/Azure), auto-scaling, CDN. Containers, LB <a href=\"/guides/how-to-choose-crm-software\">guide</a>. , DR: RPO<15min, RTO<60min <a href=\"/guide <a href=\"/guides/saas-metrics-and-kpis\">guide</a>. s/software-evaluation-checklist\">guide</a> <a href=\"/guides/email-marketing-pricing-guide\">guide</a>. . . Decision-makers evaluating enterprise so <a href=\"/guides/analytics-pricing-guide\">guide</a>. ftware must balance feature depth against total cost of ownership, considering implementation complexity, training requirements, and long-term scalability alongside immediate functional requirements and budget constraints. This approach enables teams to maximize their software investment while maintaining operational excellence.</section><section class=\"prose max-w-none mb-8\"><h2 class=\"text-2xl font-semibold mb-4\">Performance Benchmarks</h2>Sub-second P50, <2s P99. Uptime 99.9%. Global CDN, auto-scalin <a href=\"/g <a href=\"/reviews/pipedrive\">Pipedrive</a>. lossary/churn-rate\">glossary</a>. g. Decision-ma <a href=\"/g <a href=\"/glossary/roi\">glossary</a>. uides/how-to-c <a href=\"/glossary/devops\">glossary</a>. hoose-accounting-software\">guide</a>. kers evaluating enterprise software must balance feature depth against total cost of ownership, considering implementation complexity, training requirements, and long-term scalability alongside immediate functional requirements and budget constraints. This approach enables teams to maximize their software investment while maintaining operational excellence.</section><section class=\"prose max-w-none mb-8\"><h2 class=\"text-2xl font-semibold mb-4\">Category Breakdown</h2>1) best-password-managers (4/5) - . Competitive op <a href=\"/guides/accounting-softwa <a href=\"/guides/how-to-choose-accounting-software\">guide</a>. re-pricing\">guide</a>. tion. The competitive landscap <a href=\"/guides/how-to-choose-an- <a href=\"/guides/crm-pricing-guide\">guide</a>. ai-writing-tool\">guide</a>. e continues to evolve rapidly, <a href=\"/industries/landscaping\"> <a href=\"/use-cases/best-security-for-enterprise\">use case</a>. Landscaping software</a>.  with vendors investing heavily in AI capabilities, security certifications, and integration ecosystems to differentiate their offerings and capture market share across diverse industry verticals. This approach enables teams to maximize their software investment while maintaining operational excellence. 2-5) Alternatives with distinct strengths. Decision matrix enable <a href=\"/industries/nonprofit\">Nonprofit software</a>. s objective comparison. Decisi <a href=\"/industries/education\">Ed <a href=\"/industries/public-relations\">Public Relations software</a>. ucation software</a>. on-makers evaluating enterprise software must balance feature depth against total cost of ownership, considering implementation complexity, training requirements, and long-term scalability alongside immediate functional requirements and budget constraints. Organizations see measurable improvements in efficiency and user satisfaction within the first quarter of adoption.</section><section class=\"prose max-w-none mb-8\"><h2 class=\"text-2xl font-semibold mb-4\">Decision Matrix</h2>Features 25%, Ease 20%, Support 15%, Pricing 15%,  <a href=\"/best/best-analytics-software\">guide</a>. Security 15%, <a href=\"/best/best-monitoring-tools\">guide</a>.  Integration 10%. best <a href=\"/best/best-expense-management-software\">guide</a>. -password-managers: 80/100. Best fo <a href=\"/best/best-bi-tools\">guide</a>. r mid-market. Industry analysis reveals that organizations prioritizing structured evaluation processes and proof-of-concept validation achieve substantially higher satisfaction rates and lower churn compared to those making selection decisions based primarily on feature checklists or pricing considerations. This approach enables teams to maximize their software investment while maintaining operational excellence.</section><section class=\"prose max-w-none mb-8\"><h2 class=\"text-2xl font-semibold mb-4\">Implementation Timeline</h2>Wk1: Discovery. Wk2: Config, SSO, integrations. Plan workshops. W <a href=\"/reviews/zoom\">Zoom< <a href=\"/best/best-bi-tools\">guide</a>. /a>. k3-4: Migration Medium. Phased <a href=\"/best/best-consent-management-platforms\">best security & compliance</a>.  appr <a href=\"/reviews/make\">Make</a>. oach. Wk5: Testing. Wk6: Launch. Industry analysis reveals that organizations prioritizing structured evaluation processes and proof-of-concept validation achieve substantially higher satisfaction rates and lower churn compared to those making selection decisions based primarily on feature checklists or pricing considerations. This approach enables teams to maximize their software investment while maintaining operational excellence.</section><section class=\"prose max-w-none mb-8\"><h2 class=\"text-2xl font-semibold mb-4\">ROI Framework</h2>Direct: consolidation 20-40%, automation 25-35%. Indirect: productivity, accurac <a href=\"/glossary/crm\">glossary</a>. y. <a href=\"/glossary/freem <a href=\"/best/best-analytics-software\">guide</a>. iu <a href=\"/best/best-expense-management-software\">guide</a>. m\">glossary</a>.  B <a href=\"/glossary/video-conferencing\">glossary</a>. reak-even 3-6mo. Year 1: 150-300%. Decision-makers evaluating enterprise software must balance feature depth against total cost of ownership, considering implementation complexity, training requirements, and long-term scalability alongside immediate functional requirements and budget constraints. This approach enables teams to maximize their software investment while maintaining operational excellence.</section><section class=\"prose max-w-none mb-8\"><h2 class=\"text-2xl font-semibold mb-4\">Common Pitfalls</h2>Over-customizing, neglecting training, weak integration testing, no change management, und <a  <a  <a href=\"/guides/how-to-choose-an-ai-writing-tool\">guide</a>. href=\"/use-cases/best-security-for-enterprise\">use case</a>. href=\"/industries/landscaping\">Landscaping software</a>. efined success metrics. Enterprise deployments consistently demonstrate that organizations achieve significant improvements in operational efficiency and team productivity when leveraging modern software solutions tailored to their specific requirements. This approach enables teams to maximize their software investment while maintaining operational excellence.</section><section class=\"prose max-w-none mb-8\"><h2 class=\"text-2xl font-semibold mb-4\">Migration Strategy</h2>Medium complexity. Phase 1: audit (1-2wk). Phase 2: parallel (2-4wk). Ph <a href=\"/glossary/devops\">glossary</a>. ase 3: cutover <a href=\"/guides/accoun <a href=\"/glossary/churn-rate\">glossary</a>. ting-software-pricing\">guide</a>.  (1- <a href=\"/guides/how-to-choose-accounting-software\">guide</a>. 2wk). Phase 4: stabilize. Decision <a href=\"/guides/crm-pricing-guide\">guide</a>. -makers evaluating enterprise software must balance feature depth against total cost of ownership, considering implementation complexity, training requirements, and long-term scalability alongside immediate functional requirements and budget constraints. This approach enables teams to maximize their software investment while maintaining operational excellence.</section><section class=\"prose max-w-none mb-8\"><h2 class=\"text-2xl font-semibold mb-4\">Future Trends</h2>Security & Compliance evolving: AI, real-time analytics, com <a href=\"/industries/healthca <a href=\"/industries/landscap <a href=\"/use-cases/best-security-for-enterprise\">use case</a>. ing\">Landscaping software</a>. re\">Healthcare software</a>. posable architecture. best-password-mana <a href=\"/industries/construc <a href=\"/industries/printing\">Printing & Publishing software</a>. tion\">Construction software</a>. gers invests in ecosystem, Monthly. Decision-makers evaluating enterprise software must balance feature depth against total cost of ownership, considering implementation complexity, training requirements, and long-term scalability alongside immediate functional requirements and budget constraints. This approach enables teams to maximize their software investment while maintaining operational excellence.</section><section class=\"mt-8 p-6 bg-blue-50 rounded-lg border border-blue-200\"><h2 class=\"text-xl font-semibold mb-2\">Methodology</h2><p class=\"text-sm text-gray-600\">Our rankings are based on 100+ data points across 50+ security & compliance platforms, hands-on testing, user sentiment analysis, security evaluation, and market research.</p></section></article>",
  "wordCount": 2318
}